vistenum/__init__.py
vistenum/_auto.py
vistenum/_enum_box.py
vistenum/_enum_object.py
vistenum/_enum_space.py
vistenum/_vist_enu_meta.py
vistenum-0.1.7.dist-info/LICENSE
vistenum-0.1.7.dist-info/METADATA
vistenum-0.1.7.dist-info/WHEEL
vistenum-0.1.7.dist-info/top_level.txt
vistenum-0.1.7.dist-info/RECORD
