Metadata-Version: 2.1
Name: vistenum
Version: 0.1.7
Summary: opinionated 'enum' implementation.
Home-page: https://github.com/AsgerJon/vistenum
Author: Asger Jon Vistisen
Author-email: Asger Jon Vistisen <asgerjon2@gmail.com>
Project-URL: Homepage, https://github.com/AsgerJon/vistenum
Project-URL: Bug Tracker, https://github.com/AsgerJon/vistenum
Classifier: Programming Language :: Python :: 3
Classifier: License :: OSI Approved :: GNU Affero General Public License v3 or later (AGPLv3+)
Classifier: Operating System :: OS Independent
Requires-Python: >=3.11
License-File: LICENSE
